{
    "title": "Sekai Seifuku: 4-koma no Zvezda",
    "thumbnail": {
        "src": "https://cdn.myanimelist.net/images/manga/3/147939.jpg",
        "alt": "sekai-seifuku-4-koma-no-zvezda"
    },
    "type": "manga",
    "volumes": "1",
    "original_name": "世界征服〜4 コマのズヴィズダー〜",
    "start_date": "2014-01-22",
    "end_date": "2014-01-22",
    "tags": [
        "comedy",
        "fantasy"
    ],
    "authors": [
        "hunting cap brothers (Story)",
        "Hori (Story & Art)"
    ],
    "links": [
        {
            "text": "My Anime list",
            "link": "https://myanimelist.net/manga/66741/Sekai_Seifuku__4-koma_no_Zvezda"
        }
    ]
}