{
    "title": "Oshigoto wa Anata no Hanayome",
    "type": "light-novel",
    "volumes": "1",
    "chapters": "6",
    "original_name": "お仕事は貴方の花嫁",
    "start_date": "2014-07-03",
    "tags": [
        "romance",
        "josei"
    ],
    "authors": [
        "Mizushima",
        "Shinobu (Story)",
        "Haruna",
        "Hinako (Art)"
    ],
    "links": [
        {
            "text": "My Anime list",
            "link": "https://myanimelist.net/manga/101724/Oshigoto_wa_Anata_no_Hanayome"
        }
    ]
}