{
    "title": "Inumarudashi",
    "thumbnail": {
        "src": "https://cdn.myanimelist.net/images/manga/2/52041.jpg",
        "alt": "inumarudashi"
    },
    "type": "manga",
    "volumes": "11",
    "chapters": "182",
    "original_name": "いぬまるだしっ",
    "start_date": "2008-08-25",
    "end_date": "2008-08-25",
    "tags": [
        "comedy",
        "school",
        "shounen",
        "slice-of-life"
    ],
    "authors": [
        "Ooishi",
        "Kouji (Story & Art)"
    ],
    "sinopse": "The kindergartener hero Inumaru's chaotic life as he causes lively and funny incidents in this gag manga. Inumaru is just a little strange, with his deep knowledge of celebrity and Shonen Jump gossip, and his stubborn policy of not wearing pants. His teacher Tamako is given the run around everyday! This popular serial is around 9 pages each week, sometimes with just a little color thrown in!!\n\n(Source: MU)",
    "links": [
        {
            "text": "My Anime list",
            "link": "https://myanimelist.net/manga/10105/Inumarudashi"
        }
    ]
}