{
    "title": "Death March kara Hajimaru Isekai Kyousoukyoku Extra: Arisa Oujo no Isekai Funtouki",
    "thumbnail": {
        "src": "https://cdn.myanimelist.net/images/manga/2/210714.jpg",
        "alt": "death-march-kara-hajimaru-isekai-kyousoukyoku-extra-arisa-oujo-no-isekai-funtouki"
    },
    "type": "manga",
    "volumes": "1",
    "chapters": "6",
    "original_name": "デスマーチからはじまる異世界狂想曲 Ex アリサ王女の異世界奮闘記",
    "start_date": "2018-02-09",
    "end_date": "2018-02-09",
    "tags": [
        "fantasy",
        "shounen"
    ],
    "authors": [
        "Segami",
        "Akira (Art)",
        "Ainana",
        "Hiro (Story)"
    ],
    "links": [
        {
            "text": "My Anime list",
            "link": "https://myanimelist.net/manga/112238/Death_March_kara_Hajimaru_Isekai_Kyousoukyoku_Extra__Arisa_Oujo_no_Isekai_Funtouki"
        }
    ]
}