{
    "title": "Sore Ike! Anpanman: Happy no Daibouken",
    "type": "movie",
    "episodes": "1",
    "original_name": "それいけ! アンパンマン ハピーの大冒険",
    "start_date": "2005-07-16",
    "rating": "PG - Children",
    "tags": [
        "comedy"
    ],
    "sinopse": "17th Anpanman movie.",
    "links": [
        {
            "text": "My Anime list",
            "link": "https://myanimelist.net/anime/17215/Sore_Ike_Anpanman__Happy_no_Daibouken"
        },
        {
            "text": "Official Site",
            "link": "http://www.ntv.co.jp/anpanman/movie2005/"
        },
        {
            "text": "AnimeDB",
            "link": "http://anidb.info/perl-bin/animedb.pl?show=anime&aid=7561"
        },
        {
            "text": "AnimeNewsNetwork",
            "link": "http://www.animenewsnetwork.com/encyclopedia/anime.php?id=6689"
        },
        {
            "text": "Wikipedia",
            "link": "http://ja.wikipedia.org/wiki/%E3%81%9D%E3%82%8C%E3%81%84%E3%81%91!%E3%82%A2%E3%83%B3%E3%83%91%E3%83%B3%E3%83%9E%E3%83%B3_%E3%83%8F%E3%83%94%E3%83%BC%E3%81%AE%E5%A4%A7%E5%86%92%E9%99%BA"
        }
    ]
}