{
    "title": "Gensou Suikoden IV",
    "thumbnail": {
        "src": "https://cdn.myanimelist.net/images/manga/2/150296.jpg",
        "alt": "gensou-suikoden-iv"
    },
    "type": "light-novel",
    "volumes": "3",
    "original_name": "幻想水滸伝 IV",
    "start_date": "2005-09-10",
    "end_date": "2005-09-10",
    "tags": [
        "action",
        "adventure",
        "drama",
        "fantasy",
        "magic",
        "super-power",
        "supernatural",
        "military"
    ],
    "authors": [
        "Takase",
        "Mie (Story)",
        "Kawano",
        "Junko (Art)"
    ],
    "links": [
        {
            "text": "My Anime list",
            "link": "https://myanimelist.net/manga/86357/Gensou_Suikoden_IV"
        }
    ]
}