{
    "title": "Tetsu no Shojo Jun",
    "type": "manga",
    "volumes": "1",
    "chapters": "3",
    "original_name": "鉄の処女 JUN",
    "start_date": "1983-05-15",
    "end_date": "1983-05-15",
    "tags": [
        "action",
        "comedy",
        "ecchi",
        "martial-arts",
        "seinen"
    ],
    "authors": [
        "Nagai",
        "Go (Story & Art)"
    ],
    "sinopse": "Jun's 18th birthday has been selected by family tradition to be the day that her husband is chosen. Many high-class families have come to try to marry into the physically and economically powerful Asuka dynasty, but Jun is not interested. With her servant Kratta in tow, she runs away from the groom-choosing party.\n\n(Source: MU)",
    "links": [
        {
            "text": "My Anime list",
            "link": "https://myanimelist.net/manga/8560/Tetsu_no_Shojo_Jun"
        }
    ]
}