{
    "title": "5-tsu Kazoereba Kimi no Yume",
    "thumbnail": {
        "src": "https://cdn.myanimelist.net/images/manga/2/135475.jpg",
        "alt": "5-tsu-kazoereba-kimi-no-yume"
    },
    "type": "manga",
    "volumes": "1",
    "chapters": "6",
    "original_name": "5 つ数えれば君の夢",
    "start_date": "2014-02-20",
    "end_date": "2014-02-20",
    "tags": [
        "drama",
        "slice-of-life"
    ],
    "authors": [
        "Kyou",
        "Machiko (Story & Art)"
    ],
    "sinopse": "Set within the backdrop of an all girls high school where a cultural festival is about to be held. The happiness and conflicts of five girls are told.\n\n(Source: AsianWiki)",
    "links": [
        {
            "text": "My Anime list",
            "link": "https://myanimelist.net/manga/78221/5-tsu_Kazoereba_Kimi_no_Yume"
        }
    ]
}