{
    "title": "Uchi no Tantei Shirimasen ka?",
    "type": "manga",
    "volumes": "1",
    "chapters": "5",
    "original_name": "ウチの探偵知りませんか？",
    "start_date": "2007-01-20",
    "end_date": "2007-01-20",
    "tags": [
        "action",
        "comedy",
        "yaoi"
    ],
    "authors": [
        "Kisaragi",
        "Hirotaka (Story & Art)"
    ],
    "sinopse": "Ryuu and Shigure are detectives, but times are tight and they're both working in a gay bar to make ends meet. Though they're lovers, they get interrupted a lot. Will life ever calm down for these two?",
    "links": [
        {
            "text": "My Anime list",
            "link": "https://myanimelist.net/manga/5106/Uchi_no_Tantei_Shirimasen_ka"
        }
    ]
}