{
    "title": "Jugemu",
    "thumbnail": {
        "src": "https://cdn.myanimelist.net/images/manga/1/195402.jpg",
        "alt": "jugemu"
    },
    "type": "manga",
    "original_name": "ジュゲム",
    "start_date": "2017-04-28",
    "tags": [
        "shounen",
        "supernatural"
    ],
    "authors": [
        "Monri",
        "Kei (Story & Art)"
    ],
    "links": [
        {
            "text": "My Anime list",
            "link": "https://myanimelist.net/manga/106309/Jugemu"
        }
    ]
}