{
    "title": "Jue Ding",
    "type": "ona",
    "episodes": "26",
    "original_name": "绝顶",
    "start_date": "2021-02-06",
    "end_date": "2021-02-06",
    "rating": "PG-13 - Teens 13 or older",
    "tags": [
        "comedy",
        "historical"
    ],
    "sinopse": "No synopsis information has been added to this title. Help improve our database by adding a synopsis here.",
    "links": [
        {
            "text": "My Anime list",
            "link": "https://myanimelist.net/anime/46630/Jue_Ding"
        },
        {
            "text": "Official Site",
            "link": "https://v.qq.com/detail/m/mzc00200egk2zsh.html"
        },
        {
            "text": "Wikipedia",
            "link": "https://baike.baidu.com/item/%E7%BB%9D%E9%A1%B6/53190072"
        }
    ]
}