{
    "title": "Shijin no Shougai",
    "type": "movie",
    "episodes": "1",
    "original_name": "詩人の生涯",
    "start_date": "1974-01-01",
    "rating": "PG - Children",
    "tags": [
        "drama",
        "fantasy",
        "psychological"
    ],
    "sinopse": "A worker is fired from a factory for demanding a wage increase. His mother, worn thin by poverty, is caught in her own spinning wheel. Then a strange storm buries the town in snow, freezing rich and poor alike. Another short film by Kihachiro Kawamoto",
    "links": [
        {
            "text": "My Anime list",
            "link": "https://myanimelist.net/anime/7257/Shijin_no_Shougai"
        },
        {
            "text": "AnimeDB",
            "link": "http://anidb.info/perl-bin/animedb.pl?show=anime&aid=4400"
        },
        {
            "text": "AnimeNewsNetwork",
            "link": "http://www.animenewsnetwork.com/encyclopedia/anime.php?id=7379"
        },
        {
            "text": "Wikipedia",
            "link": "http://en.wikipedia.org/wiki/Kihachir%C5%8D_Kawamoto"
        }
    ]
}