{
    "title": "Under the Glass Moon",
    "type": "manhwa",
    "volumes": "3",
    "chapters": "18",
    "original_name": "유리달 아래서",
    "tags": [
        "action",
        "supernatural"
    ],
    "authors": [
        "Ko",
        "Ya Seong (Story & Art)"
    ],
    "sinopse": "Under the Glass Moon is a supernatural gothic fantasy from Korea. Wizards and witches with a fetishist/androgynous fashion sense ... think (Harry Potter meets Edward Scissorhands) Luka Reinhardt is the 21st century's greatest Dark Wizard and he has an amazing sense of fashion, to boot! He and his bookish sorcerer brother, Luel, live next door to two lovely witches, Madame Batolli and her witch-apprentice daughter, Nell. Relationships ensue...\n\n(Source: MU)",
    "links": [
        {
            "text": "My Anime list",
            "link": "https://myanimelist.net/manga/558/Under_the_Glass_Moon"
        }
    ]
}