{
    "title": "Hidoku Shinaide: Takanashi Akira-hen",
    "thumbnail": {
        "src": "https://cdn.myanimelist.net/images/manga/1/164465.jpg",
        "alt": "hidoku-shinaide-takanashi-akira-hen"
    },
    "type": "manga",
    "volumes": "1",
    "chapters": "6",
    "original_name": "酷くしないで 小鳥遊彰編",
    "start_date": "2014-02-07",
    "end_date": "2014-02-07",
    "tags": [
        "drama",
        "romance",
        "yaoi",
        "slice-of-life"
    ],
    "authors": [
        "Nekota",
        "Yonezou (Story & Art)"
    ],
    "sinopse": "A spin-off of Hidoku Shinaide that tells Akira's story.",
    "links": [
        {
            "text": "My Anime list",
            "link": "https://myanimelist.net/manga/93105/Hidoku_Shinaide__Takanashi_Akira-hen"
        }
    ]
}