{
    "title": "Hajimemashite Sekai.: Tenshi to Akuma to Hajimeru, Owaranai Tabi",
    "thumbnail": {
        "src": "https://cdn.myanimelist.net/images/manga/3/185828.jpg",
        "alt": "hajimemashite-sekai-tenshi-to-akuma-to-hajimeru-owaranai-tabi"
    },
    "type": "light-novel",
    "original_name": "はじめまして世界。 天使と悪魔と始める、終わらない旅",
    "start_date": "2016-11-19",
    "tags": [
        "fantasy"
    ],
    "authors": [
        "LLO (Art)",
        "Kazusa",
        "Tomohiro (Story)"
    ],
    "links": [
        {
            "text": "My Anime list",
            "link": "https://myanimelist.net/manga/102658/Hajimemashite_Sekai__Tenshi_to_Akuma_to_Hajimeru_Owaranai_Tabi"
        }
    ]
}