{
    "title": "Shiotaiou no Satou-san ga Ore ni dake Amai",
    "thumbnail": {
        "src": "https://cdn.myanimelist.net/images/manga/1/243324.jpg",
        "alt": "shiotaiou-no-satou-san-ga-ore-ni-dake-amai"
    },
    "type": "light-novel",
    "original_name": "塩対応の佐藤さんが俺にだけ甘い",
    "start_date": "2019-12-18",
    "tags": [
        "comedy",
        "romance"
    ],
    "authors": [
        "Sawatari",
        "Kazami (Story)",
        "Atiki (Art)"
    ],
    "links": [
        {
            "text": "My Anime list",
            "link": "https://myanimelist.net/manga/135563/Shiotaiou_no_Satou-san_ga_Ore_ni_dake_Amai"
        }
    ]
}