{
    "title": "Eromanga-sensei OVA",
    "thumbnail": {
        "src": "https://cdn.myanimelist.net/images/anime/1582/96343.jpg",
        "alt": "eromanga-sensei-ova"
    },
    "type": "ova",
    "episodes": "2",
    "original_name": "エロマンガ先生 OVA",
    "start_date": "2019-01-16",
    "opening_song": "\"Hitorigoto (ヒトリゴト)\" by ClariS (ep 2)",
    "ending_song": "\"adrenaline!!!\" by TrySail",
    "rating": "PG-13 - Teens 13 or older",
    "tags": [
        "comedy",
        "drama",
        "ecchi",
        "romance"
    ],
    "sinopse": "Yamada Elf's Love Song\n\nAs a novelist with works getting adapted into anime, Elf Yamada holds an event to celebrate her success and to thank everyone who had supported her. With her mother attending, she becomes more excited. However, just as her mother arrives, she tells Elf to go back home so that she can find a suitable husband. Elf, who harbors feelings for Masamune Izumi, chooses to say no…\n\nCooked Meals of Pure Love\n\nWinter has come, and it's freezing outside. With her brother Masamune catching a cold, Sagiri Izumi decides to nurse her brother into good health by stepping outside the comfort of her room and doing the housework herself.\n\n[Source My Anime List]",
    "links": [
        {
            "text": "My Anime list",
            "link": "https://myanimelist.net/anime/36792/Eromanga-sensei_OVA"
        },
        {
            "text": "Official Site",
            "link": "http://eromanga-sensei.com/"
        },
        {
            "text": "AnimeDB",
            "link": "http://anidb.info/perl-bin/animedb.pl?show=anime&aid=13580"
        },
        {
            "text": "Wikipedia",
            "link": "https://en.wikipedia.org/wiki/Eromanga_Sensei"
        }
    ]
}