{
    "title": "Sengoku Basara 3: Kishin no Gotoku",
    "type": "manga",
    "volumes": "1",
    "chapters": "4",
    "original_name": "戦国 BASARA3~鬼神の如く~",
    "start_date": "2012-09-24",
    "tags": [
        "action",
        "shoujo"
    ],
    "authors": [
        "Higuchi",
        "Daisuke (Art)",
        "Capcom (Story)"
    ],
    "sinopse": "A manga that follows Chousokabe Motochika's storyline in Sengoku Basara 3.",
    "links": [
        {
            "text": "My Anime list",
            "link": "https://myanimelist.net/manga/73689/Sengoku_Basara_3__Kishin_no_Gotoku"
        }
    ]
}