{
    "title": "Pocke Loli",
    "type": "light-novel",
    "volumes": "2",
    "chapters": "14",
    "original_name": "ポケロリ",
    "start_date": "2005-09-30",
    "end_date": "2005-09-30",
    "tags": [
        "adventure",
        "comedy",
        "fantasy",
        "romance"
    ],
    "authors": [
        "Takei",
        "Touka (Story)",
        "Ikegami",
        "Akane (Art)"
    ],
    "links": [
        {
            "text": "My Anime list",
            "link": "https://myanimelist.net/manga/61481/Pocke_Loli"
        }
    ]
}