{
    "title": "Kotowaza Gundam-san (ONA)",
    "thumbnail": {
        "src": "https://cdn.myanimelist.net/images/anime/4/79832.jpg",
        "alt": "kotowaza-gundam-san-ona"
    },
    "type": "ona",
    "episodes": "17",
    "original_name": "ことわざガンダムさん",
    "start_date": "2015-02-18",
    "end_date": "2015-02-18",
    "rating": "PG-13 - Teens 13 or older",
    "tags": [
        "comedy",
        "parody",
        "mecha"
    ],
    "sinopse": "No synopsis information has been added to this title. Help improve our database by adding a synopsis here.",
    "links": [
        {
            "text": "My Anime list",
            "link": "https://myanimelist.net/anime/33226/Kotowaza_Gundam-san_ONA"
        },
        {
            "text": "Wikipedia",
            "link": "https://ja.wikipedia.org/wiki/機動戦士ガンダムさん"
        }
    ]
}