{
    "title": "Black Tiger",
    "type": "manga",
    "original_name": "BLACK TIGER",
    "start_date": "2016-12-21",
    "tags": [
        "action",
        "historical",
        "seinen"
    ],
    "authors": [
        "Akimoto",
        "Osamu (Story & Art)"
    ],
    "sinopse": "The \"intense gun action\" story is set in the United States in the aftermath of the American Civil War. In the chaotic atmosphere of the postwar period, the northern government issues \"Licenses to Kill\" to bounty hunters in order for them to take out the South's remaining soldiers and outlaws. One of those bounty hunters, a female gunslinger known as \"Black Tiger,\" faces off against dark enemies who carry fiendish weapons.\n\n(Source: ANN)",
    "links": [
        {
            "text": "My Anime list",
            "link": "https://myanimelist.net/manga/101828/Black_Tiger"
        }
    ]
}