{
    "title": "Love Like Crazy",
    "type": "manhwa",
    "volumes": "11",
    "original_name": "사랑에 미쳐라",
    "start_date": "2007-05-18",
    "end_date": "2007-05-18",
    "tags": [
        "drama",
        "romance",
        "school",
        "shoujo"
    ],
    "authors": [
        "Hwang",
        "Mi Ri (Story & Art)"
    ],
    "sinopse": "Han Se In finds street fighter Moon Ji Soo collapsed on the street. When she tries to help him he tells her to go away, Se In wants an apology but Ji Soon wont give one. She then slaps him and runs, Moon Ji Soon wants revenge...\n\n(Source: MangaFox)",
    "links": [
        {
            "text": "My Anime list",
            "link": "https://myanimelist.net/manga/6957/Love_Like_Crazy"
        }
    ]
}