{
    "title": "Kimi wo Shiru Tabi ni Koi wo Suru",
    "thumbnail": {
        "src": "https://cdn.myanimelist.net/images/manga/1/57599.jpg",
        "alt": "kimi-wo-shiru-tabi-ni-koi-wo-suru"
    },
    "type": "manga",
    "volumes": "1",
    "chapters": "6",
    "original_name": "君を知るたびに恋をする",
    "start_date": "2011-01-20",
    "tags": [
        "yaoi"
    ],
    "authors": [
        "Isaka",
        "Juugorou (Story & Art)"
    ],
    "links": [
        {
            "text": "My Anime list",
            "link": "https://myanimelist.net/manga/31277/Kimi_wo_Shiru_Tabi_ni_Koi_wo_Suru"
        }
    ]
}