{
    "title": "Oboreru Kemono to Amai Wana",
    "thumbnail": {
        "src": "https://cdn.myanimelist.net/images/manga/2/172421.jpg",
        "alt": "oboreru-kemono-to-amai-wana"
    },
    "type": "manga",
    "chapters": "22",
    "original_name": "溺れる獣と甘い罠",
    "start_date": "2015-03-14",
    "end_date": "2015-03-14",
    "tags": [
        "drama",
        "romance"
    ],
    "authors": [
        "Matsuzaki",
        "Maho (Story)",
        "Juri",
        "Hakamada (Art)"
    ],
    "links": [
        {
            "text": "My Anime list",
            "link": "https://myanimelist.net/manga/96635/Oboreru_Kemono_to_Amai_Wana"
        }
    ]
}