{
    "title": "B♭ no Sonata",
    "thumbnail": {
        "src": "https://cdn.myanimelist.net/images/manga/2/142921.jpg",
        "alt": "b♭-no-sonata"
    },
    "type": "manga",
    "volumes": "1",
    "chapters": "20",
    "original_name": "B♭ のソナタ",
    "tags": [
        "comedy",
        "dementia",
        "slice-of-life",
        "psychological"
    ],
    "authors": [
        "Fukuyama",
        "Youji (Story & Art)"
    ],
    "sinopse": "Collection of short stories, many of which seem to have to do with copies/doppelgangers.\n\n1. Monotorogy\n2. Topologie\n3. Nagaaaai Yoru\n4. Pimple Pimple Little Star\n5. To Love Again\n6. Kotenteki Hatsumehin ni yoru Kotenteki Paradox no Pattern\n7. Katei, Shiyuu Zaisan, Kokka no Kigen\n8. Haru Random\n9. \"Boshizou\"\n10. Kontora Bass Dokusou ni Yoru Mubansou Sonata Hen Rochouchuo Andante\n11. Tenraku no Ballade\n12. Manatsu no Yoru no Masayume\n13. Itoshi no Remy\n14. Le Chateau\n15. Zuisou\n16. Communication Break Down?\n17. Buta mo Ki kara Ochiru\n18. Fukuyamanga Kyoushikyoku\n19. Naive\n20. Schizophrenia",
    "links": [
        {
            "text": "My Anime list",
            "link": "https://myanimelist.net/manga/82439/B%E2%99%AD_no_Sonata"
        }
    ]
}