{
    "title": "Motomegami no Blog",
    "thumbnail": {
        "src": "https://cdn.myanimelist.net/images/manga/3/203933.jpg",
        "alt": "motomegami-no-blog"
    },
    "type": "manga",
    "original_name": "元女神のブログ",
    "start_date": "2017-05-01",
    "tags": [
        "comedy",
        "fantasy",
        "slice-of-life"
    ],
    "authors": [
        "Honma",
        "Makoto (Story & Art)"
    ],
    "links": [
        {
            "text": "My Anime list",
            "link": "https://myanimelist.net/manga/111080/Motomegami_no_Blog"
        }
    ]
}