{
    "title": "Cold Light",
    "thumbnail": {
        "src": "https://cdn.myanimelist.net/images/manga/2/30522.jpg",
        "alt": "cold-light"
    },
    "type": "light-novel",
    "volumes": "1",
    "chapters": "4",
    "original_name": "COLD LIGHT",
    "start_date": "2004-04-15",
    "tags": [
        "drama",
        "romance",
        "yaoi"
    ],
    "authors": [
        "Konohara",
        "Narise (Story)",
        "Saikawa",
        "Nanao (Art)"
    ],
    "sinopse": "Fujishima's wound he suffered from protecting Tooru has healed and he's finally been released from the hospital. Their life together starts again once more. Tooru wants them to live together as lovers, but Fujishima refuses, saying \"I have no intentions of loving you.\" Is Fujishima afraid of Tooru remembering something in particular if he regains his memories? The bonds of the past are finally becoming clearer...\n\n(Source: MU)",
    "links": [
        {
            "text": "My Anime list",
            "link": "https://myanimelist.net/manga/19605/Cold_Light"
        }
    ]
}