{
    "title": "Oazuke no Scenario",
    "thumbnail": {
        "src": "https://cdn.myanimelist.net/images/manga/3/223393.jpg",
        "alt": "oazuke-no-scenario"
    },
    "type": "manga",
    "volumes": "1",
    "chapters": "6",
    "original_name": "おあずけのシナリオ",
    "start_date": "2017-11-30",
    "end_date": "2017-11-30",
    "tags": [
        "yaoi"
    ],
    "authors": [
        "Umi",
        "Tomoshibi (Story & Art)"
    ],
    "links": [
        {
            "text": "My Anime list",
            "link": "https://myanimelist.net/manga/114629/Oazuke_no_Scenario"
        }
    ]
}