{
    "title": "Kamisama wa Tabun Hidarikiki",
    "thumbnail": {
        "src": "https://cdn.myanimelist.net/images/manga/3/228382.jpg",
        "alt": "kamisama-wa-tabun-hidarikiki"
    },
    "type": "manga",
    "volumes": "1",
    "chapters": "6",
    "original_name": "神様はたぶん左利き",
    "start_date": "2016-06-24",
    "end_date": "2016-06-24",
    "tags": [
        "drama",
        "shounen-ai"
    ],
    "authors": [
        "Mushiba (Story & Art)"
    ],
    "sinopse": "Determined to pay off his father's debts, Yano works to create counterfeit money for the yakuza. Though he is really good, Yano can't quite make his \"artificial\" money perfect. That is, until he has Makura, a man skilled at art and creating counterfeits, thrust onto him by the yakuza. Given permission to use him anyway he wants... how will Yano use his human copy machine?\n\n(Source: Fantasista Inc.)",
    "links": [
        {
            "text": "My Anime list",
            "link": "https://myanimelist.net/manga/124943/Kamisama_wa_Tabun_Hidarikiki"
        }
    ]
}