{
    "title": "ToriPiki",
    "thumbnail": {
        "src": "https://cdn.myanimelist.net/images/manga/2/193989.jpg",
        "alt": "tori-piki"
    },
    "type": "manga",
    "volumes": "2",
    "chapters": "30",
    "original_name": "とりぴき",
    "start_date": "2016-10-31",
    "end_date": "2016-10-31",
    "tags": [
        "comedy",
        "supernatural"
    ],
    "authors": [
        "Kuze",
        "Ran (Story & Art)"
    ],
    "sinopse": "The story of the human Youta Akise and the tengu Asupa.",
    "links": [
        {
            "text": "My Anime list",
            "link": "https://myanimelist.net/manga/105905/ToriPiki"
        }
    ]
}