{
    "title": "Readyyy!",
    "type": "ona",
    "episodes": "1",
    "original_name": "Readyyy!",
    "start_date": "2018-08-26",
    "rating": "G - All Ages",
    "tags": [
        "music"
    ],
    "sinopse": "The opening animation to Readyyy!, Sega's male idol training smartphone game. The game is set in Kamakura, and the story's protagonist is a newly-minted producer of the Dia Production talent agency. But the protagonist is also the manager of the dormitory where 18 idols are all living together.\n\nPre-registration opened the day after the video was posted to the official YouTube channel but there has been no release date listed as to when the app will launch.\n\n(Source: ANN)",
    "links": [
        {
            "text": "My Anime list",
            "link": "https://myanimelist.net/anime/38485/Readyyy"
        },
        {
            "text": "Official Site",
            "link": "http://ready.sega.jp/"
        }
    ]
}