{
    "title": "Youkoso Uchuujin",
    "type": "movie",
    "episodes": "1",
    "original_name": "ようこそ宇宙人",
    "start_date": "2066-01-19",
    "rating": "G - All Ages",
    "tags": [
        "comedy"
    ],
    "sinopse": "Stop motion animation of aliens on a guided tour around an amusement park.\n\n(Source: AniDB)",
    "links": [
        {
            "text": "My Anime list",
            "link": "https://myanimelist.net/anime/13087/Youkoso_Uchuujin"
        },
        {
            "text": "AnimeDB",
            "link": "http://anidb.info/perl-bin/animedb.pl?show=anime&aid=8988"
        }
    ]
}