{
    "title": "Fairy Gone 2nd Season",
    "type": "tv-serie",
    "episodes": "12",
    "original_name": "Fairy gone フェアリーゴーン 第 2 期",
    "start_date": "2019-10-07",
    "end_date": "2019-10-07",
    "opening_song": "\"STILL STANDING\" by (K)NoW_NAME",
    "ending_song": "\"Stay Gold\" by (K)NoW_NAME",
    "rating": "PG-13 - Teens 13 or older",
    "tags": [
        "action",
        "demons",
        "supernatural",
        "magic",
        "fantasy"
    ],
    "sinopse": "Second season of Fairy Gone.",
    "links": [
        {
            "text": "My Anime list",
            "link": "https://myanimelist.net/anime/39811/Fairy_Gone_2nd_Season"
        },
        {
            "text": "Official Site",
            "link": "https://www.fairygone.com/"
        },
        {
            "text": "AnimeDB",
            "link": "http://anidb.info/perl-bin/animedb.pl?show=anime&aid=14916"
        },
        {
            "text": "AnimeNewsNetwork",
            "link": "http://www.animenewsnetwork.com/encyclopedia/anime.php?id=22341"
        },
        {
            "text": "Wikipedia",
            "link": "https://en.wikipedia.org/wiki/Fairy_Gone"
        }
    ]
}