{
    "title": "IS: Infinite Stratos - Koushiki Anthology Comic",
    "type": "manga",
    "volumes": "1",
    "chapters": "11",
    "original_name": "IS〈インフィニット・ストラトス〉 【公式】アンソロジーコミック",
    "start_date": "2011-09-22",
    "tags": [
        "comedy",
        "ecchi",
        "romance",
        "harem"
    ],
    "authors": [
        "Kuromasa",
        "Shisei (Story & Art)",
        "Yamaki",
        "Rin (Story & Art)",
        "BLADE (Story & Art)",
        "Asakawa",
        "Keiji (Story & Art)",
        "Shinozuka",
        "Atsuto (Story & Art)",
        "Akaboshi",
        "Kenji (Story & Art)",
        "Ishigami",
        "Kazui (Story & Art)",
        "Kazahana",
        "Chiruwo (Story & Art)",
        "Kon",
        "Takuto (Story & Art)"
    ],
    "sinopse": "An anthology comic of Infinite Stratos by various mangaka.",
    "links": [
        {
            "text": "My Anime list",
            "link": "https://myanimelist.net/manga/33837/IS__Infinite_Stratos_-_Koushiki_Anthology_Comic"
        }
    ]
}