{
    "title": "Watashi wa S ni Sakaraenai",
    "thumbnail": {
        "src": "https://cdn.myanimelist.net/images/manga/1/226085.jpg",
        "alt": "watashi-wa-s-ni-sakaraenai"
    },
    "type": "manga",
    "volumes": "6",
    "chapters": "32",
    "original_name": "私は S に逆らえない",
    "start_date": "2017-11-20",
    "end_date": "2017-11-20",
    "tags": [
        "drama",
        "romance",
        "shoujo"
    ],
    "authors": [
        "Hibiki",
        "Ai (Story & Art)"
    ],
    "sinopse": "To pay for her father’s debts. Poor, virgin Miku ended up applying to be the lover of a distantly related CEO, and takes \"lover lessons\" from a handsome butler. On the sofa of a mansion... in a suite of a high class hotel... undergoing H lectures from the butler causes Miku who is a virgin to weaken...!?\n\n(Source: Shogakukan, translated)\n\nIncluded one-shots:\nVolume 2: Choukyou Ganbou Bangaihen\nVolume 6: Tonari no Nudist: Sekirara☆Love",
    "links": [
        {
            "text": "My Anime list",
            "link": "https://myanimelist.net/manga/121722/Watashi_wa_S_ni_Sakaraenai"
        }
    ]
}