{
    "title": "Ikasete!! Bambina♥",
    "type": "manga",
    "volumes": "3",
    "chapters": "29",
    "original_name": "イかせて！！バンビーナ ♥",
    "start_date": "2006-10-20",
    "end_date": "2006-10-20",
    "tags": [
        "comedy",
        "romance",
        "supernatural",
        "seinen"
    ],
    "authors": [
        "Kanzaki",
        "Masaomi (Story & Art)"
    ],
    "sinopse": "Yutaro Minatomo is a young 15 -year-old high school student who wants a girlfriend, but his terrible luck and shyness keep him from accomplishing his dream. qui aimerait par dessus tout avoir une petite amie. One day, his crush Yumeko calls him to meet her at the top of the school. Yutaro decides to take this chance to confess his love, but he ends up shocked by what he sees at their meeting point!\n\nThe heartbroken Yutaro stops believing in love and unknowingly summons Bambina, a wonderul woman who calls herself a Knight of Love. This female Cupid will turn Yutaro's life upside down!",
    "links": [
        {
            "text": "My Anime list",
            "link": "https://myanimelist.net/manga/45421/Ikasete_Bambina%E2%99%A5"
        }
    ]
}