{
    "title": "Seishun Zettai Tsubusuman na Ore ni Sukuihairanai.",
    "thumbnail": {
        "src": "https://cdn.myanimelist.net/images/manga/1/193867.jpg",
        "alt": "seishun-zettai-tsubusuman-na-ore-ni-sukuihairanai"
    },
    "type": "light-novel",
    "original_name": "青春絶対つぶすマンな俺に救いはいらない。",
    "start_date": "2017-04-18",
    "tags": [
        "comedy",
        "romance",
        "school"
    ],
    "authors": [
        "Sakaida",
        "Yoshitaka (Story)",
        "U35 (Art)"
    ],
    "links": [
        {
            "text": "My Anime list",
            "link": "https://myanimelist.net/manga/105892/Seishun_Zettai_Tsubusuman_na_Ore_ni_Sukuihairanai"
        }
    ]
}