{
    "title": "Zoku Ai Ore! - Danshikou no Hime to Joshikou no Ouji",
    "thumbnail": {
        "src": "https://cdn.myanimelist.net/images/manga/1/104227.jpg",
        "alt": "zoku-ai-ore-danshikou-no-hime-to-joshikou-no-ouji"
    },
    "type": "manga",
    "volumes": "3",
    "chapters": "3",
    "original_name": "続・愛俺! 〜男子校の姫と女子校の王子〜",
    "start_date": "2012-10-18",
    "end_date": "2012-10-18",
    "tags": [
        "shoujo"
    ],
    "authors": [
        "Shinjou",
        "Mayu (Story & Art)"
    ],
    "sinopse": "2 years have passed since then, and now before indecent couple appears mysterious boy and girl. And they ask them respectively on a date. The boy ask Akira, and the girl, Mizuki... Where will it take them that twisted love relationship?\nShinjou Mayu's first time digital kakioroshi continuation is here!",
    "links": [
        {
            "text": "My Anime list",
            "link": "https://myanimelist.net/manga/60477/Zoku_Ai_Ore_-_Danshikou_no_Hime_to_Joshikou_no_Ouji"
        }
    ]
}