{
    "title": "Fire Emblem: Kakusei Comic Anthology",
    "type": "manga",
    "volumes": "2",
    "chapters": "27",
    "original_name": "ファイアーエムブレム 覚醒 コミックアンソロジー",
    "start_date": "2014-12-25",
    "end_date": "2014-12-25",
    "tags": [
        "comedy",
        "fantasy"
    ],
    "authors": [
        "Tonami",
        "Minato (Story & Art)",
        "Emiri (Story & Art)",
        "Nagao",
        "Uka (Story & Art)",
        "Kirai",
        "Yuu (Story & Art)"
    ],
    "sinopse": "An anthology of short vanilla one-shots based on the Nintendo 3DS game Fire Emblem drawn by various mangaka.",
    "links": [
        {
            "text": "My Anime list",
            "link": "https://myanimelist.net/manga/90100/Fire_Emblem__Kakusei_Comic_Anthology"
        }
    ]
}