{
    "title": "Nisekon!",
    "thumbnail": {
        "src": "https://cdn.myanimelist.net/images/manga/1/206582.jpg",
        "alt": "nisekon"
    },
    "type": "manga",
    "volumes": "2",
    "chapters": "18",
    "original_name": "ニセ婚！",
    "start_date": "2014-05-30",
    "end_date": "2014-05-30",
    "tags": [
        "ecchi",
        "romance",
        "seinen"
    ],
    "authors": [
        "Sawada",
        "Furope (Story & Art)"
    ],
    "links": [
        {
            "text": "My Anime list",
            "link": "https://myanimelist.net/manga/110315/Nisekon"
        }
    ]
}