{
    "title": "Toukarl Sheep Hon Mura",
    "thumbnail": {
        "src": "https://cdn.myanimelist.net/images/manga/2/64699.jpg",
        "alt": "toukarl-sheep-hon-mura"
    },
    "type": "manga",
    "volumes": "2",
    "chapters": "10",
    "original_name": "東カール・シープホーン村",
    "start_date": "2003-05-20",
    "tags": [
        "fantasy",
        "shoujo"
    ],
    "authors": [
        "Shitou",
        "Kyouko (Story & Art)"
    ],
    "sinopse": "Marian's parents promised to return in 4 days, but they have not been heard from for 4 weeks. In the meantime, Marian has been living at her relative's place. One morning, she wakes up to find herself in a village where everyone looks like animals, but behave and talk like humans.",
    "links": [
        {
            "text": "My Anime list",
            "link": "https://myanimelist.net/manga/35683/Toukarl_Sheep_Hon_Mura"
        }
    ]
}