{
    "title": "Ai Yuugi",
    "thumbnail": {
        "src": "https://cdn.myanimelist.net/images/manga/1/63115.jpg",
        "alt": "ai-yuugi"
    },
    "type": "manga",
    "volumes": "1",
    "chapters": "4",
    "original_name": "愛・遊戯",
    "start_date": "2005-01-20",
    "tags": [
        "drama",
        "romance",
        "shoujo",
        "harem"
    ],
    "authors": [
        "Mashiki",
        "Hisame (Story & Art)"
    ],
    "sinopse": "Juying is a huge fan of mega superstar Jack Lee. In order to rearrange her feelings from a failed relationship, she flew alone to Jack's country. However, upon arrival at Hong Kong she was dragged into things by suspicious men. At the height of danger, a man who looks like Jack appeared to her rescue...\n\nContains 3 oneshots:\nIt Just Has To Be You\nStrawberry House\nA Willful Love\n\n(Source: MU)",
    "links": [
        {
            "text": "My Anime list",
            "link": "https://myanimelist.net/manga/34695/Ai_Yuugi"
        }
    ]
}