{
    "title": "Suki to Ienai...",
    "thumbnail": {
        "src": "https://cdn.myanimelist.net/images/manga/3/28241.jpg",
        "alt": "suki-to-ienai"
    },
    "type": "manga",
    "volumes": "1",
    "original_name": "好きと言えない・・・",
    "tags": [
        "romance",
        "school",
        "shoujo"
    ],
    "authors": [
        "Nakaji",
        "Yuki (Story & Art)"
    ],
    "sinopse": "Ryouta likes Miyako but she always be nice to Ryouta's older brother instead. One day Ryouta's brother got back from his University from Tokyo with his girlfriend.",
    "links": [
        {
            "text": "My Anime list",
            "link": "https://myanimelist.net/manga/18436/Suki_to_Ienai"
        }
    ]
}