{
    "title": "Isekai Gardening: Al no Zouen Monogatari",
    "thumbnail": {
        "src": "https://cdn.myanimelist.net/images/manga/2/174873.jpg",
        "alt": "isekai-gardening-al-no-zouen-monogatari"
    },
    "type": "light-novel",
    "original_name": "異世界ガーデニング アルの造園物語",
    "start_date": "2016-01-09",
    "tags": [
        "fantasy"
    ],
    "authors": [
        "wingheart (Art)",
        "Kanbutsuya (Story)"
    ],
    "links": [
        {
            "text": "My Anime list",
            "link": "https://myanimelist.net/manga/97749/Isekai_Gardening__Al_no_Zouen_Monogatari"
        }
    ]
}