{
    "title": "Short Cuts",
    "type": "manga",
    "volumes": "2",
    "chapters": "10",
    "original_name": "ショートカッツ",
    "start_date": "1996-10-03",
    "end_date": "1996-10-03",
    "tags": [
        "comedy",
        "ecchi",
        "parody",
        "seinen"
    ],
    "authors": [
        "Furuya",
        "Usamaru (Story & Art)"
    ],
    "sinopse": "Short Cuts is a manga series by Usamaru Furuya, released in two volumes and originally published in Young Sunday magazine. Each volume contains approximately one hundred 'cuts', short comics which typically span only one or two pages. The primary theme of Short Cuts is Japanese kogal and youth culture, which is tackled with a heavy use of visual jokes, black humor and sex comedy.",
    "links": [
        {
            "text": "My Anime list",
            "link": "https://myanimelist.net/manga/1229/Short_Cuts"
        }
    ]
}