{
    "title": "Ohayou! Kokekkou-san",
    "type": "tv-serie",
    "episodes": "50",
    "original_name": "おはよう! コケッコーさん",
    "start_date": "2016-10-02",
    "end_date": "2016-10-02",
    "rating": "G - All Ages",
    "tags": [
        "comedy"
    ],
    "sinopse": "Kokekkou-san is a mother hen in a big chicken family. Keeping everyone and everything right is not an easy job for her.\n\n(Source: ANN)",
    "links": [
        {
            "text": "My Anime list",
            "link": "https://myanimelist.net/anime/34234/Ohayou_Kokekkou-san"
        },
        {
            "text": "Official Site",
            "link": "http://www.tv-tokyo.co.jp/anime/kinder/"
        },
        {
            "text": "AnimeDB",
            "link": "http://anidb.info/perl-bin/animedb.pl?show=anime&aid=12469"
        },
        {
            "text": "AnimeNewsNetwork",
            "link": "http://www.animenewsnetwork.com/encyclopedia/anime.php?id=18784"
        }
    ]
}