{
    "title": "100-oku Nengo no Kimi no Koe mo",
    "type": "manga",
    "volumes": "1",
    "original_name": "100 億年後のきみの声も",
    "start_date": "2004-11-12",
    "tags": [
        "drama",
        "shoujo",
        "yuri"
    ],
    "authors": [
        "Akiyama",
        "Maiko (Story)",
        "Okai",
        "Haruko (Art)"
    ],
    "sinopse": "1. Honnou to Senshokutai (Instinct and a Chromosome)",
    "links": [
        {
            "text": "My Anime list",
            "link": "https://myanimelist.net/manga/11317/100-oku_Nengo_no_Kimi_no_Koe_mo"
        }
    ]
}