{
    "title": "Maou no Musume, Sugoku Choroi.",
    "type": "manga",
    "original_name": "魔王の娘、すごくチョロい。",
    "start_date": "2020-06-16",
    "tags": [
        "comedy",
        "demons",
        "fantasy",
        "magic"
    ],
    "authors": [
        "Chiaki",
        "Tarou (Story & Art)"
    ],
    "sinopse": "In the final showdown between the Demon King and the Hero, the latter used all his power to seal away the former. To exact her revenge on her father's nemesis, the Demon King's daughter, Hel, resurrected the Hero and planned to use him as her personal servant. However, the resurrected Hero is unexpectedly dazzling and dashing, and Hel's composure begins to waver. Will she ever be able to torment her new servant?\n\n(Source: Akita Shoten, translated)",
    "links": [
        {
            "text": "My Anime list",
            "link": "https://myanimelist.net/manga/130255/Maou_no_Musume_Sugoku_Choroi"
        }
    ]
}