{
    "title": "Nana-iro Kakumei",
    "thumbnail": {
        "src": "https://cdn.myanimelist.net/images/manga/1/165397.jpg",
        "alt": "nana-iro-kakumei"
    },
    "type": "manga",
    "volumes": "8",
    "original_name": "なないろ革命",
    "start_date": "2014-08-02",
    "end_date": "2014-08-02",
    "tags": [
        "comedy",
        "school",
        "shoujo"
    ],
    "authors": [
        "Yuzuhara",
        "Mizuka (Story & Art)"
    ],
    "sinopse": "Ever since primary school, Nana has never been able to refuse the wishes of her friend, Yuyu, even if they were unpleasant things like matching outfits and hairstyles... She wanted to change herself!\n\nA story about real friendship and sympathy.\n\n(Source: MU)",
    "links": [
        {
            "text": "My Anime list",
            "link": "https://myanimelist.net/manga/89341/Nana-iro_Kakumei"
        }
    ]
}