{
    "title": "Power Harassment Bishoujo Company",
    "thumbnail": {
        "src": "https://cdn.myanimelist.net/images/manga/2/226647.jpg",
        "alt": "power-harassment-bishoujo-company"
    },
    "type": "manga",
    "volumes": "3",
    "chapters": "66",
    "original_name": "パワハラ美少女カンパニー",
    "start_date": "2017-11-22",
    "end_date": "2017-11-22",
    "tags": [
        "comedy"
    ],
    "authors": [
        "Hiroma",
        "Gekka (Story & Art)"
    ],
    "sinopse": "The company employee Osanai is upset, because his superior, a middle-aged man, abuses him at work every single day. One day Osanai ends up drinking his pain away and accidentally buys glasses which promise to make middle-aged men look like beautiful girls. His everyday life changes drastically...\n\n(Source: Shueisha, translated)",
    "links": [
        {
            "text": "My Anime list",
            "link": "https://myanimelist.net/manga/114261/Power_Harassment_Bishoujo_Company"
        }
    ]
}