{
    "title": "Scarecrowman",
    "type": "tv-serie",
    "episodes": "26",
    "original_name": "スケアクロウマン",
    "start_date": "2008-07-03",
    "end_date": "2008-07-03",
    "opening_song": "\"Halo Glow －ハロウグロウ－\" by Kohei Dojima",
    "ending_song": "\"Ashita, Boku wa (あした、僕は)\" by Takako Tate",
    "rating": "G - All Ages",
    "tags": [
        "fantasy"
    ],
    "sinopse": "A regular old scarecrow has stood in a field for twenty years when one day, after a lightning storm, he comes to life. He becomes friends with the daughter of a scarecrow shop owner.",
    "links": [
        {
            "text": "My Anime list",
            "link": "https://myanimelist.net/anime/4684/Scarecrowman"
        },
        {
            "text": "Official Site",
            "link": "http://www.vap.co.jp/scarecrowman/"
        },
        {
            "text": "AnimeDB",
            "link": "http://anidb.info/perl-bin/animedb.pl?show=anime&aid=6023"
        },
        {
            "text": "AnimeNewsNetwork",
            "link": "http://www.animenewsnetwork.com/encyclopedia/anime.php?id=10045"
        }
    ]
}